helpdesk_client/.DS_Store
helpdesk_client/__init__.py
helpdesk_client/enums.py
helpdesk_client/exceptions.py
helpdesk_client/py.typed
helpdesk_client/types_.py
helpdesk_client/utils.py
helpdesk_client/v3/__init__.py
helpdesk_client/v3/client.py
helpdesk_client/v3/dto.py
helpdesk_client/v3/schemas/__init__.py
helpdesk_client/v3/schemas/body.py
helpdesk_client/v3/schemas/pagination.py
helpdesk_client/v3/schemas/query_params.py
helpdesk_client/v3/schemas/response.py
helpdesk_client/v3/urls.py
servicedesk_client-0.4.3.dist-info/METADATA
servicedesk_client-0.4.3.dist-info/WHEEL
servicedesk_client-0.4.3.dist-info/entry_points.txt
servicedesk_client-0.4.3.dist-info/RECORD
