Metadata-Version: 2.1
Name: servicedesk-client
Version: 0.4.3
Summary: API client for ServiceDesk Plus
Author-Email: Strana Dev <pypi@stranadev.ru>
License: MIT
Project-URL: Repository, https://github.com/stranadev/helpdesk-client
Requires-Python: >=3.11
Requires-Dist: httpx>=0.27.0
Requires-Dist: pydantic>=2.8.2
Requires-Dist: orjson>=3.10.6
